README.rst
setup.cfg
setup.py
base65536/__about__.py
base65536/__init__.py
base65536/core.py
base65536.egg-info/PKG-INFO
base65536.egg-info/SOURCES.txt
base65536.egg-info/dependency_links.txt
base65536.egg-info/requires.txt
base65536.egg-info/top_level.txt