Metadata-Version: 1.0
Name: base65536
Version: 0.1.1
Summary: Base-65536 Python implementation
Home-page: https://github.com/Parkayun/base65536
Author: Ayun Park
Author-email: iamparkayun@gmail.com
License: UNKNOWN
Keywords: Base-65536
Platform: UNKNOWN
